elasticsearch_watcher/__init__.py
elasticsearch_watcher/watcher.py
elasticsearch_watcher-0.4.0.dist-info/DESCRIPTION.rst
elasticsearch_watcher-0.4.0.dist-info/METADATA
elasticsearch_watcher-0.4.0.dist-info/metadata.json
elasticsearch_watcher-0.4.0.dist-info/RECORD
elasticsearch_watcher-0.4.0.dist-info/top_level.txt
elasticsearch_watcher-0.4.0.dist-info/WHEEL
