Metadata-Version: 2.0
Name: elasticsearch-watcher
Version: 0.4.0
Summary: Python client for Elasticsearch Watcher
Home-page: https://github.com/elastic/elasticsearch-watcher-py
Author: Honza Král
Author-email: honza.kral@gmail.com
License: Apache License, Version 2.0
Platform: UNKNOWN
Classifier: Development Status :: 4 - Beta
Classifier: License :: OSI Approved :: Apache Software License
Classifier: Intended Audience :: Developers
Classifier: Operating System :: OS Independent
Classifier: Programming Language :: Python
Classifier: Programming Language :: Python :: 2
Classifier: Programming Language :: Python :: 2.6
Classifier: Programming Language :: Python :: 2.7
Classifier: Programming Language :: Python :: 3
Classifier: Programming Language :: Python :: 3.2
Classifier: Programming Language :: Python :: 3.3
Classifier: Programming Language :: Python :: 3.4
Classifier: Programming Language :: Python :: Implementation :: CPython
Classifier: Programming Language :: Python :: Implementation :: PyPy
Requires-Dist: elasticsearch (>=1.5.0,<2.0.0)
